automatic_narratives/__init__.py
automatic_narratives/automatic_narratives.py
automatic_narratives-0.0.6.dist-info/METADATA
automatic_narratives-0.0.6.dist-info/WHEEL
automatic_narratives-0.0.6.dist-info/top_level.txt
automatic_narratives-0.0.6.dist-info/RECORD
