Metadata-Version: 2.4
Name: automatic_narratives
Version: 0.0.6
Summary: This package lets one infer agency and communion codes from life narratives based on RoBERTa transformer embeddings.
Author-email: Johannes Klinz <johannes.klinz@gmail.com>
License: MIT
Requires-Python: >=3.10
Requires-Dist: numpy>=2.2.5
Requires-Dist: pandas>=2.2.3
Requires-Dist: scikit-learn==1.5.1
Requires-Dist: torch>=2.7.0
Requires-Dist: transformers>=4.51.3
